arxiv_public_data/__init__.py
arxiv_public_data/authors.py
arxiv_public_data/config.py
arxiv_public_data/fixunicode.py
arxiv_public_data/fulltext.py
arxiv_public_data/internal_citations.py
arxiv_public_data/oai_metadata.py
arxiv_public_data/pdfstamp.py
arxiv_public_data/regex_arxiv.py
arxiv_public_data/s3_bulk_download.py
arxiv_public_data/slice_pdfs.py
arxiv_public_data/tex2utf.py
arxiv_public_data/embeddings/__init__.py
arxiv_public_data/embeddings/tf_hub.py
arxiv_public_data/embeddings/util.py
Auto_Research-1.0.dist-info/LICENSE
Auto_Research-1.0.dist-info/METADATA
Auto_Research-1.0.dist-info/WHEEL
Auto_Research-1.0.dist-info/entry_points.txt
Auto_Research-1.0.dist-info/top_level.txt
Auto_Research-1.0.dist-info/RECORD
