Metadata-Version: 2.1
Name: Auto-Research
Version: 1.0
Summary: Geberate scientific survey with just a query
Home-page: https://github.com/sidphbot/Auto-Research
Author: Sidharth Pal
Author-email: sidharth.pal1992@gmail.com
License: UNKNOWN
Project-URL: Docs, https://github.com/example/example/README.md
Project-URL: Bug Tracker, https://github.com/sidphbot/Auto-Research/issues
Project-URL: Demo, https://www.kaggle.com/sidharthpal/auto-research-generate-survey-from-query
Platform: UNKNOWN
Classifier: Development Status :: 5 - Production/Stable
Classifier: Environment :: Console
Classifier: Environment :: Other Environment
Classifier: Intended Audience :: Developers
Classifier: Intended Audience :: Education
Classifier: Intended Audience :: Science/Research
Classifier: Intended Audience :: Other Audience
Classifier: Topic :: Education
Classifier: Topic :: Education :: Computer Aided Instruction (CAI)
Classifier: Topic :: Scientific/Engineering
Classifier: Topic :: Scientific/Engineering :: Artificial Intelligence
Classifier: Topic :: Scientific/Engineering :: Information Analysis
Classifier: Topic :: Scientific/Engineering :: Medical Science Apps.
Classifier: Topic :: Scientific/Engineering :: Physics
Classifier: Natural Language :: English
Classifier: License :: OSI Approved :: GNU General Public License (GPL)
Classifier: License :: OSI Approved :: GNU Library or Lesser General Public License (LGPL)
Classifier: License :: OSI Approved :: GNU Lesser General Public License v3 or later (LGPLv3+)
Classifier: License :: OSI Approved :: GNU General Public License v3 or later (GPLv3+)
Classifier: Operating System :: POSIX :: Linux
Classifier: Operating System :: MacOS :: MacOS X
Classifier: Environment :: GPU
Classifier: Environment :: GPU :: NVIDIA CUDA
Classifier: Programming Language :: Python
Classifier: Programming Language :: Python :: 3
Classifier: Programming Language :: Python :: 3 :: Only
Classifier: Programming Language :: Python :: 3.6
Requires-Python: >=3.7
License-File: LICENSE
Requires-Dist: pip
Requires-Dist: boto3 (==1.9.118)
Requires-Dist: requests (==2.20.0)
Requires-Dist: unicodedata2 (==11.0.0)
Requires-Dist: pdfminer
Requires-Dist: sentence-transformers
Requires-Dist: pdftotext
Requires-Dist: arxiv
Requires-Dist: arxiv2bib
Requires-Dist: scholarly
Requires-Dist: PyMuPDF (==1.18.14)
Requires-Dist: Pillow
Requires-Dist: tabula-py
Requires-Dist: sentencepiece
Requires-Dist: keybert
Requires-Dist: spacy[all]
Requires-Dist: scispacy
Requires-Dist: amrlib
Requires-Dist: transformers
Requires-Dist: neuralcoref
Requires-Dist: en-core-sci-scibert
Requires-Dist: en-core-sci-lg
Requires-Dist: bert-extractive-summarizer
